odoo/addons/partner_display_name_line_break/README.rst
odoo/addons/partner_display_name_line_break/__init__.py
odoo/addons/partner_display_name_line_break/__manifest__.py
odoo/addons/partner_display_name_line_break/i18n/it.po
odoo/addons/partner_display_name_line_break/i18n/partner_address_two_lines.pot
odoo/addons/partner_display_name_line_break/i18n/partner_display_name_line_break.pot
odoo/addons/partner_display_name_line_break/models/__init__.py
odoo/addons/partner_display_name_line_break/models/ir_actions_report.py
odoo/addons/partner_display_name_line_break/models/res_partner.py
odoo/addons/partner_display_name_line_break/readme/CONTRIBUTORS.md
odoo/addons/partner_display_name_line_break/readme/CREDITS.md
odoo/addons/partner_display_name_line_break/readme/DESCRIPTION.md
odoo/addons/partner_display_name_line_break/static/description/icon.png
odoo/addons/partner_display_name_line_break/static/description/index.html
odoo/addons/partner_display_name_line_break/tests/__init__.py
odoo/addons/partner_display_name_line_break/tests/test_res_partner.py
odoo_addon_partner_display_name_line_break-17.0.1.0.1.dist-info/METADATA
odoo_addon_partner_display_name_line_break-17.0.1.0.1.dist-info/WHEEL
odoo_addon_partner_display_name_line_break-17.0.1.0.1.dist-info/top_level.txt
odoo_addon_partner_display_name_line_break-17.0.1.0.1.dist-info/RECORD
